datatables/__init__.py
datatables/base.py
datatables/datatable.py
datatables/py.typed
sqlalchemy2_datatables-0.6.2.dist-info/METADATA
sqlalchemy2_datatables-0.6.2.dist-info/WHEEL
sqlalchemy2_datatables-0.6.2.dist-info/licenses/LICENCE
sqlalchemy2_datatables-0.6.2.dist-info/RECORD
