Metadata-Version: 2.1
Name: sqlalchemy2-datatables
Version: 0.6.2
Summary: Python Sqlalchemy 2.0 based serverside processing for jQuery datatables.
Project-URL: Homepage, https://github.com/coding-doc/sqlalchemy2-datatables
Author-email: "R. Hannes Niedner" <hniedner@gmail.com>
License-Expression: MIT
License-File: LICENCE
Classifier: Development Status :: 3 - Alpha
Classifier: Environment :: Web Environment
Classifier: Intended Audience :: Developers
Classifier: Intended Audience :: Information Technology
Classifier: Intended Audience :: System Administrators
Classifier: License :: OSI Approved :: MIT License
Classifier: Operating System :: OS Independent
Classifier: Programming Language :: Python
Classifier: Programming Language :: Python :: 3
Classifier: Programming Language :: Python :: 3 :: Only
Classifier: Programming Language :: Python :: 3.10
Classifier: Programming Language :: Python :: 3.11
Classifier: Topic :: Database
Classifier: Topic :: Database :: Front-Ends
Classifier: Topic :: Internet
Classifier: Topic :: Internet :: WWW/HTTP
Classifier: Topic :: Internet :: WWW/HTTP :: HTTP Servers
Classifier: Topic :: Internet :: WWW/HTTP :: Indexing/Search
Classifier: Topic :: Software Development
Classifier: Topic :: Software Development :: Libraries
Classifier: Topic :: Software Development :: Libraries :: Application Frameworks
Classifier: Topic :: Software Development :: Libraries :: Python Modules
Classifier: Typing :: Typed
Requires-Python: >=3.10
Requires-Dist: sqlalchemy~=2.0.0rc3
Provides-Extra: dev
Requires-Dist: autoflake~=2.0.0; extra == 'dev'
Requires-Dist: black[d]~=22.12.0; extra == 'dev'
Requires-Dist: coverage[toml]~=7.0.5; extra == 'dev'
Requires-Dist: hatchling~=1.12.2; extra == 'dev'
Requires-Dist: isort~=5.11.4; extra == 'dev'
Requires-Dist: mypy~=0.991; extra == 'dev'
Requires-Dist: pre-commit~=2.21.0; extra == 'dev'
Requires-Dist: pytest-cov~=4.0.0; extra == 'dev'
Requires-Dist: pytest~=7.2.0; extra == 'dev'
Requires-Dist: pyupgrade~=3.3.1; extra == 'dev'
Requires-Dist: ruff~=0.0.219; extra == 'dev'
